cpuid_native.cpython-311-x86_64-linux-gnu.so
cpuid_native-0.0.8.dist-info/RECORD
cpuid_native-0.0.8.dist-info/LICENSE
cpuid_native-0.0.8.dist-info/WHEEL
cpuid_native-0.0.8.dist-info/METADATA
cpuid_native-0.0.8.dist-info/top_level.txt
